_jsonnet.cp39-win_amd64.pyd
jsonnet_binary-0.17.0.dist-info/LICENSE
jsonnet_binary-0.17.0.dist-info/METADATA
jsonnet_binary-0.17.0.dist-info/WHEEL
jsonnet_binary-0.17.0.dist-info/top_level.txt
jsonnet_binary-0.17.0.dist-info/RECORD
