Metadata-Version: 2.1
Name: jsonnet-binary
Version: 0.17.0
Summary: An UNOFFICIAL Python interface to Jsonnet, available as whl packages for Mac, Linux and Windows.
Home-page: https://github.com/Toilal/python-jsonnet-binary
Author: Matt Covalt
Author-email: mcovalt@mailbox.org
Maintainer: Rémi Alvergnat
Maintainer-email: toilal.dev@gmail.com
License: UNKNOWN
Platform: UNKNOWN
